omniidl/__init__.py
omniidl/idlast.py
omniidl/idltype.py
omniidl/idlutil.py
omniidl/idlvisitor.py
omniidl/main.py
omniidl/output.py
omniidl-4.2.2.dist-info/METADATA
omniidl-4.2.2.dist-info/RECORD
omniidl-4.2.2.dist-info/WHEEL
omniidl-4.2.2.dist-info/top_level.txt
