Metadata-Version: 2.1
Name: omniidl
Version: 4.2.2
Summary: omniidl library for writing backends
Home-page: http://omniorb.sourceforge.net/
Author: Kevin Kuehler, Tommy Yuan
Author-email: Kevin.Kuehler@viasat.com, Tommy.Yuan@viasat.com
License: LGPLv2.1
Keywords: omniidl omniiorb corba orb
Platform: UNKNOWN
Classifier: Programming Language :: Python :: 2
Classifier: Programming Language :: Python :: 2.7
Classifier: Programming Language :: Python :: 3
Classifier: Programming Language :: Python :: 3.4
Classifier: Programming Language :: Python :: 3.5
Classifier: Programming Language :: Python :: 3.6
Classifier: Operating System :: OS Independent
